IM_COOL_BOOY_QR/__init__.py
IM_COOL_BOOY_QR/__main__.py
IM_COOL_BOOY_QR/init.py
IM_COOL_BOOY_QR/main.py
im_cool_booy_qr-1.2.0.dist-info/licenses/LICENSE
im_cool_booy_qr-1.2.0.dist-info/METADATA
im_cool_booy_qr-1.2.0.dist-info/WHEEL
im_cool_booy_qr-1.2.0.dist-info/entry_points.txt
im_cool_booy_qr-1.2.0.dist-info/top_level.txt
im_cool_booy_qr-1.2.0.dist-info/RECORD
