Metadata-Version: 2.4
Name: IM-COOL-BOOY-QR
Version: 1.2.0
Summary: Stylish QR Code generator with logo, colors, and text options
Author: coolbooy
Author-email: coolbooy@gmail.com
License: MIT
Keywords: QR
Classifier: Programming Language :: Python :: 3
Classifier: License :: OSI Approved :: MIT License
Classifier: Operating System :: OS Independent
Classifier: Intended Audience :: Developers
Requires-Python: >=3.6
License-File: LICENSE
Requires-Dist: qrcode
Requires-Dist: Pillow
Requires-Dist: colorama
Dynamic: author
Dynamic: author-email
Dynamic: classifier
Dynamic: description
Dynamic: description-content-type
Dynamic: keywords
Dynamic: license
Dynamic: license-file
Dynamic: requires-dist
Dynamic: requires-python
Dynamic: summary
